roboauto/__init__.py
roboauto/book.py
roboauto/chat.py
roboauto/date_utils.py
roboauto/global_state.py
roboauto/gpg_key.py
roboauto/info.py
roboauto/keep_online.py
roboauto/logger.py
roboauto/order.py
roboauto/order_action.py
roboauto/order_data.py
roboauto/order_local.py
roboauto/requests_api.py
roboauto/robot.py
roboauto/subprocess_commands.py
roboauto/utils.py
roboauto-0.4.0.data/scripts/roboauto
roboauto-0.4.0.dist-info/LICENSE
roboauto-0.4.0.dist-info/METADATA
roboauto-0.4.0.dist-info/WHEEL
roboauto-0.4.0.dist-info/top_level.txt
roboauto-0.4.0.dist-info/RECORD
