Metadata-Version: 2.1
Name: roboauto
Version: 0.4.0
Summary: robosats cli
Home-page: https://github.com/jerryfletcher21/roboauto
Author: jerryfletcher21
Author-email: jerryfletcher@cock.email
License: ISC
Classifier: Development Status :: 4 - Beta
Classifier: Environment :: Console
Classifier: Intended Audience :: Developers
Classifier: License :: OSI Approved :: ISC License (ISCL)
Classifier: Operating System :: POSIX
Classifier: Operating System :: Unix
Classifier: Programming Language :: Python
Classifier: Programming Language :: Unix Shell
Classifier: Topic :: Software Development
Classifier: Topic :: System :: Shells
Classifier: Topic :: Utilities
License-File: LICENSE
